first_last_frame/__init__.py
first_last_frame-1767774.631.530.dist-info/licenses/LICENSE
first_last_frame-1767774.631.530.dist-info/METADATA
first_last_frame-1767774.631.530.dist-info/WHEEL
first_last_frame-1767774.631.530.dist-info/top_level.txt
first_last_frame-1767774.631.530.dist-info/RECORD
